<?xml version="1.0" encoding="UTF-8"?>
<BaliMessageLog>
    <Task name="Export">
        <Message>
            <ID>1081100</ID>
            <Severity>1</Severity>
            <Dynamic>Bitstream authenticated.</Dynamic>
        </Message>
        <Message>
            <ID>77001032</ID>
            <Severity>16</Severity>
            <Dynamic>CTRL0_IN</Dynamic>
            <Dynamic>ldc_set_location -site {13} [get_ports CTRL0_IN]</Dynamic>
        </Message>
        <Message>
            <ID>77001031</ID>
            <Severity>16</Severity>
            <Dynamic>ldc_set_location -site {13} [get_ports CTRL0_IN]</Dynamic>
        </Message>
        <Message>
            <ID>1191031</ID>
            <Severity>1</Severity>
        </Message>
    </Task>
    <Task name="PAR">
        <Message>
            <ID>77001032</ID>
            <Severity>16</Severity>
            <Dynamic>CTRL0_IN</Dynamic>
            <Dynamic>ldc_set_location -site {13} [get_ports CTRL0_IN]</Dynamic>
        </Message>
        <Message>
            <ID>77001031</ID>
            <Severity>16</Severity>
            <Dynamic>ldc_set_location -site {13} [get_ports CTRL0_IN]</Dynamic>
        </Message>
        <Message>
            <ID>70001944</ID>
            <Severity>16</Severity>
            <Dynamic>create_generated_clock -name {pll_clk_int} -source [get_pins {pll_inst/lscc_pll_inst/u_PLL_B/REFERENCECLK}] -multiply_by 4 [get_pins {pll_inst/lscc_pll_inst/u_PLL_B/OUTGLOBAL }] </Dynamic>
        </Message>
        <Message>
            <ID>77001032</ID>
            <Severity>16</Severity>
            <Dynamic>CTRL0_IN</Dynamic>
            <Dynamic>ldc_set_location -site {13} [get_ports CTRL0_IN]</Dynamic>
        </Message>
        <Message>
            <ID>77001031</ID>
            <Severity>16</Severity>
            <Dynamic>ldc_set_location -site {13} [get_ports CTRL0_IN]</Dynamic>
        </Message>
        <Message>
            <ID>71003020</ID>
            <Severity>16</Severity>
            <Dynamic>CTRL0_IN</Dynamic>
        </Message>
        <Message>
            <ID>71003020</ID>
            <Severity>16</Severity>
            <Dynamic>CTRL0_IN</Dynamic>
        </Message>
        <Message>
            <ID>71003020</ID>
            <Severity>16</Severity>
            <Dynamic>CTRL0_IN</Dynamic>
        </Message>
        <Message>
            <ID>71003020</ID>
            <Severity>16</Severity>
            <Dynamic>CTRL0_IN</Dynamic>
        </Message>
        <Message>
            <ID>70001944</ID>
            <Severity>16</Severity>
            <Dynamic>create_generated_clock -name {pll_clk_int} -source [get_pins {pll_inst/lscc_pll_inst/u_PLL_B/REFERENCECLK}] -multiply_by 4 [get_pins {pll_inst/lscc_pll_inst/u_PLL_B/OUTGLOBAL }] </Dynamic>
        </Message>
        <Message>
            <ID>77001032</ID>
            <Severity>16</Severity>
            <Dynamic>CTRL0_IN</Dynamic>
            <Dynamic>ldc_set_location -site {13} [get_ports CTRL0_IN]</Dynamic>
        </Message>
        <Message>
            <ID>77001031</ID>
            <Severity>16</Severity>
            <Dynamic>ldc_set_location -site {13} [get_ports CTRL0_IN]</Dynamic>
        </Message>
        <Message>
            <ID>77001032</ID>
            <Severity>16</Severity>
            <Dynamic>CTRL0_IN</Dynamic>
            <Dynamic>ldc_set_location -site {13} [get_ports CTRL0_IN]</Dynamic>
        </Message>
        <Message>
            <ID>77001031</ID>
            <Severity>16</Severity>
            <Dynamic>ldc_set_location -site {13} [get_ports CTRL0_IN]</Dynamic>
        </Message>
        <Message>
            <ID>70001944</ID>
            <Severity>16</Severity>
            <Dynamic>create_generated_clock -name {pll_clk_int} -source [get_pins {pll_inst/lscc_pll_inst/u_PLL_B/REFERENCECLK}] -multiply_by 4 [get_pins {pll_inst/lscc_pll_inst/u_PLL_B/OUTGLOBAL }] </Dynamic>
        </Message>
        <Message>
            <ID>70001944</ID>
            <Severity>16</Severity>
            <Dynamic>create_generated_clock -name {pll_clk_int} -source [get_pins {pll_inst/lscc_pll_inst/u_PLL_B/REFERENCECLK}] -multiply_by 4 [get_pins {pll_inst/lscc_pll_inst/u_PLL_B/OUTGLOBAL }] </Dynamic>
        </Message>
        <Message>
            <ID>70001944</ID>
            <Severity>16</Severity>
            <Dynamic>create_generated_clock -name {pll_clk_int} -source [get_pins {pll_inst/lscc_pll_inst/u_PLL_B/REFERENCECLK}] -multiply_by 4 [get_pins {pll_inst/lscc_pll_inst/u_PLL_B/OUTGLOBAL }] </Dynamic>
        </Message>
    </Task>
</BaliMessageLog>